ntnx_volumes_py_client/__init__.py
ntnx_volumes_py_client/api_client.py
ntnx_volumes_py_client/api_response.py
ntnx_volumes_py_client/configuration.py
ntnx_volumes_py_client/custom_retry.py
ntnx_volumes_py_client/rest.py
ntnx_volumes_py_client/api/__init__.py
ntnx_volumes_py_client/api/iscsi_clients_api.py
ntnx_volumes_py_client/api/nvmf_clients_api.py
ntnx_volumes_py_client/api/volume_groups_api.py
ntnx_volumes_py_client/models/__init__.py
ntnx_volumes_py_client/models/OneOfcommon/__init__.py
ntnx_volumes_py_client/models/OneOfcommon/v1/__init__.py
ntnx_volumes_py_client/models/OneOfcommon/v1/config/KVPairvalue.py
ntnx_volumes_py_client/models/OneOfcommon/v1/config/__init__.py
ntnx_volumes_py_client/models/OneOfvolumes/__init__.py
ntnx_volumes_py_client/models/OneOfvolumes/v4/__init__.py
ntnx_volumes_py_client/models/OneOfvolumes/v4/config/AssociateCategoryApiResponsedata.py
ntnx_volumes_py_client/models/OneOfvolumes/v4/config/AttachIscsiClientApiResponsedata.py
ntnx_volumes_py_client/models/OneOfvolumes/v4/config/AttachNvmfClientApiResponsedata.py
ntnx_volumes_py_client/models/OneOfvolumes/v4/config/AttachVmApiResponsedata.py
ntnx_volumes_py_client/models/OneOfvolumes/v4/config/CreateVolumeDiskApiResponsedata.py
ntnx_volumes_py_client/models/OneOfvolumes/v4/config/CreateVolumeGroupApiResponsedata.py
ntnx_volumes_py_client/models/OneOfvolumes/v4/config/DeleteVolumeDiskApiResponsedata.py
ntnx_volumes_py_client/models/OneOfvolumes/v4/config/DeleteVolumeGroupApiResponsedata.py
ntnx_volumes_py_client/models/OneOfvolumes/v4/config/DetachIscsiClientApiResponsedata.py
ntnx_volumes_py_client/models/OneOfvolumes/v4/config/DetachNvmfClientApiResponsedata.py
ntnx_volumes_py_client/models/OneOfvolumes/v4/config/DetachVmApiResponsedata.py
ntnx_volumes_py_client/models/OneOfvolumes/v4/config/DisassociateCategoryApiResponsedata.py
ntnx_volumes_py_client/models/OneOfvolumes/v4/config/GetIscsiClientApiResponsedata.py
ntnx_volumes_py_client-4.2.1.dist-info/LICENSE.txt
ntnx_volumes_py_client-4.2.1.dist-info/METADATA
ntnx_volumes_py_client-4.2.1.dist-info/WHEEL
ntnx_volumes_py_client-4.2.1.dist-info/top_level.txt
ntnx_volumes_py_client-4.2.1.dist-info/RECORD
